otc_sphinx_directives/__init__.py
otc_sphinx_directives/card_item.py
otc_sphinx_directives/container_item.py
otc_sphinx_directives/directive_wrapper.py
otc_sphinx_directives/docs_link.py
otc_sphinx_directives/document_navigator.py
otc_sphinx_directives/navigator.py
otc_sphinx_directives/otc_sphinx_directives_setup.py
otc_sphinx_directives/popular_services.py
otc_sphinx_directives/service_card.py
otc_sphinx_directives/service_card_link.py
otc_sphinx_directives/service_group.py
otc_sphinx_directives/service_navigator.py
otc_sphinx_directives/tests/__init__.py
otc_sphinx_directives/tests/base.py
otc_sphinx_directives/tests/test_directive_wrapper.py
otc_sphinx_directives/tests/test_service_card.py
otc_sphinx_directives/tests/templates/directive_wrapper/conf.py
otc_sphinx_directives/tests/templates/directive_wrapper/index.rst
otc_sphinx_directives/tests/templates/service_card/conf.py
otc_sphinx_directives/tests/templates/service_card/index.rst
otc_sphinx_directives-1.12.1.dist-info/licenses/AUTHORS
otc_sphinx_directives-1.12.1.dist-info/licenses/LICENSE
otc_sphinx_directives-1.12.1.dist-info/METADATA
otc_sphinx_directives-1.12.1.dist-info/WHEEL
otc_sphinx_directives-1.12.1.dist-info/dependency_links.txt
otc_sphinx_directives-1.12.1.dist-info/pbr.json
otc_sphinx_directives-1.12.1.dist-info/top_level.txt
otc_sphinx_directives-1.12.1.dist-info/RECORD
