Metadata-Version: 2.4
Name: otc_sphinx_directives
Version: 1.12.1
Summary: Open Telekom Cloud Sphinx Directives
Author: Open Telekom Cloud Ecosystem Squad
Keywords: Sphinx, Sphinx Directives, Open Telekom Cloud
Classifier: Framework :: Sphinx
Classifier: Intended Audience :: Information Technology
Classifier: Intended Audience :: System Administrators
Classifier: License :: OSI Approved :: Apache Software License
Classifier: Operating System :: POSIX :: Linux
Classifier: Programming Language :: Python
Classifier: Programming Language :: Python :: 3
License-File: LICENSE
License-File: AUTHORS
Requires-Dist: sphinx>=4.0.0
Requires-Dist: otc_metadata
Dynamic: author
Dynamic: classifier
Dynamic: description
Dynamic: keywords
Dynamic: license-file
Dynamic: requires-dist
Dynamic: summary
